setup.cfg
setup.py
ilmwetter/__init__.py
ilmwetter/items.py
ilmwetter/pipelines.py
ilmwetter/settings.py
ilmwetter.egg-info/PKG-INFO
ilmwetter.egg-info/SOURCES.txt
ilmwetter.egg-info/dependency_links.txt
ilmwetter.egg-info/entry_points.txt
ilmwetter.egg-info/requires.txt
ilmwetter.egg-info/top_level.txt
ilmwetter/spiders/__init__.py
ilmwetter/spiders/thedy.py