Metadata-Version: 1.0
Name: ilmwetter
Version: 0.1
Summary: Scrapy spider for the weather in Ilmenau
Home-page: UNKNOWN
Author: Wieland Hoffmann
Author-email: UNKNOWN
License: UNKNOWN
Platform: UNKNOWN
